{
    "id": 399,
    "name": "wave hard",
    "author": "brapstu",
    "creators": [],
    "verifier": "evil",
    "verification": "https://youtu.be/HQKKeluy3Yc?si=fiGMidnpe-kVpJO2",
    "percentToQualify": 100,
    "records": [
        {
            "user": "Rin",
            "link": "https://cdn.discordapp.com/attachments/1148741371532935241/1148783585038450698/wave_hard.mp4",
            "percent": 100,
            "hz": 300
        },
        {
            "user": "Rae",
            "link": "https://youtu.be/AB41TSc8UbA",
            "percent": 100,
            "hz": 360
        },
        {
            "user": "DuskOTN",
            "link": "https://discord.com/channels/923026827281317919/1148741371532935241/1209016144174911559",
            "percent": 100,
            "hz": 240
        }
    ]
}
